nn6/__init__.py
nn6/nn.py
nn6-0.0.4.dist-info/LICENSE.txt
nn6-0.0.4.dist-info/METADATA
nn6-0.0.4.dist-info/WHEEL
nn6-0.0.4.dist-info/top_level.txt
nn6-0.0.4.dist-info/RECORD
