Metadata-Version: 2.1
Name: nn6
Version: 0.0.4
Summary: nn6 -- Neural Network 6
Home-page: https://github.com/ccc-py/nn6
Author: ccckmit
Author-email: ccckmit@gmail.com
License: UNKNOWN
Platform: UNKNOWN
Classifier: Programming Language :: Python :: 3
Classifier: License :: OSI Approved :: MIT License
Classifier: Operating System :: OS Independent
Requires-Python: >=3.6
